README
ez_setup.py
setup.py
GFX.egg-info/PKG-INFO
GFX.egg-info/SOURCES.txt
GFX.egg-info/dependency_links.txt
GFX.egg-info/native_libs.txt
GFX.egg-info/top_level.txt
gfx/__init__.py
gfx/array.c
gfx/array.pyx
gfx/ext.py
gfx/gl.c
gfx/gl.pyx
