Metadata-Version: 1.0
Name: GFX
Version: 4
Summary: Basic Textured Quads and Lines using OpenGL.
Home-page: http://code.google.com/p/corsair-redux/wiki/GFX
Author: Simon Wittber
Author-email: simonwittber@gmail.com
License: MIT
Platform: Any
